aiomoe/__init__.py
aiomoe/api/__init__.py
aiomoe/api/api.py
aiomoe/errors/__init__.py
aiomoe/errors/errors.py
aiomoe/models/__init__.py
aiomoe/models/models.py
aiomoe/utils/__init__.py
aiomoe/utils/response_processor.py
aiomoe-1.0.4.dist-info/LICENSE
aiomoe-1.0.4.dist-info/WHEEL
aiomoe-1.0.4.dist-info/METADATA
aiomoe-1.0.4.dist-info/RECORD
