Metadata-Version: 2.1
Name: aiomoe
Version: 1.0.4
Summary: Fully asynchronous trace.moe API wrapper
Home-page: https://github.com/FeeeeK/aiomoe
License: MIT
Keywords: api,aiomoe,async,asyncio,trace.moe,tracemoe,tracemoe-api
Author: FeeeeK
Requires-Python: >=3.6.1,<4.0.0
Classifier: Environment :: Console
Classifier: Intended Audience :: Developers
Classifier: License :: OSI Approved :: MIT License
Classifier: Programming Language :: Python :: 3
Classifier: Programming Language :: Python :: 3.6
Classifier: Programming Language :: Python :: 3.7
Classifier: Programming Language :: Python :: 3.8
Classifier: Programming Language :: Python :: 3.9
Classifier: Topic :: Software Development :: Libraries :: Python Modules
Classifier: Topic :: Software Development :: Quality Assurance
Classifier: Typing :: Typed
Requires-Dist: aiohttp (>=3.7.4,<4.0.0)
Requires-Dist: loguru (>=0.5.3,<0.6.0)
Requires-Dist: pydantic (>=1.8.2,<2.0.0)
Project-URL: Bug Tracker, https://github.com/FeeeeK/aiomoe/issues
Project-URL: Repository, https://github.com/FeeeeK/aiomoe
